src/__init__.py
src/main.py
src/auth/__init__.py
src/auth/azure_auth.py
src/signing/__init__.py
src/signing/file_signer.py
src/utils/__init__.py
src/utils/platform_utils.py
azure_code_signer-0.1.6.dist-info/METADATA
azure_code_signer-0.1.6.dist-info/WHEEL
azure_code_signer-0.1.6.dist-info/entry_points.txt
azure_code_signer-0.1.6.dist-info/top_level.txt
azure_code_signer-0.1.6.dist-info/RECORD
