Metadata-Version: 2.4
Name: azure-code-signer
Version: 0.1.6
Summary: A command line tool to code sign files using a code signing certificate stored in Azure Key Vault.
Author-email: Attie Retief <attie@attieretief.com>
License: MIT
Project-URL: Homepage, https://github.com/attieretief/azure-code-signer
Project-URL: Bug Tracker, https://github.com/attieretief/azure-code-signer/issues
Project-URL: Source Code, https://github.com/attieretief/azure-code-signer
Project-URL: Documentation, https://github.com/attieretief/azure-code-signer#readme
Keywords: azure,key-vault,code-signing,certificate,signature,security,digital-signature,cryptography
Classifier: Development Status :: 4 - Beta
Classifier: Intended Audience :: Developers
Classifier: Intended Audience :: System Administrators
Classifier: License :: OSI Approved :: MIT License
Classifier: Programming Language :: Python :: 3
Classifier: Programming Language :: Python :: 3.7
Classifier: Programming Language :: Python :: 3.8
Classifier: Programming Language :: Python :: 3.9
Classifier: Programming Language :: Python :: 3.10
Classifier: Programming Language :: Python :: 3.11
Classifier: Programming Language :: Python :: 3.12
Classifier: Topic :: Security
Classifier: Topic :: Security :: Cryptography
Classifier: Topic :: Software Development :: Build Tools
Classifier: Topic :: System :: Software Distribution
Classifier: Operating System :: OS Independent
Requires-Python: >=3.7
Requires-Dist: azure-identity>=1.10.0
Requires-Dist: azure-keyvault-certificates>=4.5.0
Requires-Dist: azure-keyvault-secrets>=4.5.0
Requires-Dist: cryptography>=38.0.0
